.DS_Store
aist/__init__.py
aist/aist.py
aist/download.py
aist/msg.py
aist/pic.py
haochuan/__init__.py
haochuan/jiang.py
haochuan-8.8.8.dist-info/LICENSE
haochuan-8.8.8.dist-info/METADATA
haochuan-8.8.8.dist-info/WHEEL
haochuan-8.8.8.dist-info/top_level.txt
haochuan-8.8.8.dist-info/RECORD
